README.rst
setup.py
genpipeline/__init__.py
genpipeline/db.py
genpipeline.egg-info/PKG-INFO
genpipeline.egg-info/SOURCES.txt
genpipeline.egg-info/dependency_links.txt
genpipeline.egg-info/requires.txt
genpipeline.egg-info/top_level.txt