Metadata-Version: 1.1
Name: genpipeline
Version: 0.1.1
Summary: A simple Python coroutine-based method for creating data processing pipelines
Home-page: https://github.com/renshawbay/genpipeline
Author: Renshaw Bay
Author-email: technology@renshawbay.com
License: UNKNOWN
Platform: UNKNOWN
Classifier: License :: OSI Approved :: MIT License
